Telon/__init__.py
Telon/bot.py
Telon-0.2.dist-info/METADATA
Telon-0.2.dist-info/WHEEL
Telon-0.2.dist-info/top_level.txt
Telon-0.2.dist-info/RECORD
