Metadata-Version: 2.1
Name: Telon
Version: 0.2
Summary: A simple Telegram bot library using requests
Home-page: https://github.com/x7007x/TgMan
Author: Ahmed
Author-email: a7mednegm.x@example.com
Classifier: Programming Language :: Python :: 3
Classifier: License :: OSI Approved :: MIT License
Classifier: Operating System :: OS Independent
Requires-Python: >=3.6
Requires-Dist: requests>=2.24.0
